LICENSE
MANIFEST.in
README.md
VERSION
requirements.txt
setup.cfg
setup.py
dnsrecon/__init__.py
dnsrecon/__main__.py
dnsrecon.egg-info/PKG-INFO
dnsrecon.egg-info/SOURCES.txt
dnsrecon.egg-info/dependency_links.txt
dnsrecon.egg-info/entry_points.txt
dnsrecon.egg-info/requires.txt
dnsrecon.egg-info/top_level.txt
dnsrecon.egg-info/zip-safe
dnsrecon/lib/__init__.py
dnsrecon/lib/bingenum.py
dnsrecon/lib/crtenum.py
dnsrecon/lib/dnshelper.py
dnsrecon/lib/msf_print.py
dnsrecon/lib/whois.py
dnsrecon/lib/yandexenum.py
dnsrecon/wordlist/namelist.txt
dnsrecon/wordlist/snoop.txt
dnsrecon/wordlist/subdomains-top1mil-20000.txt
dnsrecon/wordlist/subdomains-top1mil-5000.txt
dnsrecon/wordlist/subdomains-top1mil.txt
tests/__init__.py