Metadata-Version: 2.1
Name: dnsrecon
Version: 0.10.1
Summary: Installable version of dnsrecon: DNS Enumeration Script
Home-page: http://github.com/cr0hn/dnsrecon
Author: Carlos Perez
Author-email: carlos_perez@darkoperator.com
Maintainer: cr0hn (maintainer)
Maintainer-email: cr0hn@cr0hn.com
License: License :: OSI Approved :: GNU General Public License v2 (GPLv2)
Platform: UNKNOWN
Classifier: Programming Language :: Python :: 3
Classifier: Programming Language :: Python :: 3.6
Classifier: Programming Language :: Python :: 3.7
Classifier: Programming Language :: Python :: 3.8
Classifier: Programming Language :: Python :: 3.9
Classifier: License :: OSI Approved :: GNU General Public License v2 (GPLv2)
Classifier: Operating System :: OS Independent
